{
  "description": "container object for all extended metrics objects",
  "type": "object",
  "required": ["day"],
  "properties": {
    "day": {
      "description": "Day this metric represents",
      "type": "string",
      "format": "date"          
    },
    "record": {
      "description": "Record metadata metric",
      "type": "array",
      "items": {
        "$ref": "record_metadata.json"
      }
    },
    "view": {
      "description": "Record view metadata metric",
      "type": "array",
      "items": {
        "$ref": "view_metadata.json"
      }
    }
  }
}
